{
  "name": "Days and Dates",
  "slug": "days-and-dates",
  "description": "In this lesson, you'll learn the days and months of the calendar.",
  "prompts": [
    "Monday",
    "Tuesday",
    "Wednesday",
    "Thursday",
    "Friday",
    "Saturday",
    "Sunday",
    "January",
    "February",
    "March",
    "April",
    "May",
    "June",
    "July",
    "August",
    "September",
    "October",
    "November",
    "December",
    "Summer",
    "Autumn",
    "Winter",
    "Spring"
  ],
  "translations": {
    "fr": [
      "lundi",
      "mardi",
      "mercredi",
      "jeudi",
      "vendredi",
      "samedi",
      "dimanche",
      "janvier",
      "février",
      "mars",
      "avril",
      "mai",
      "juin",
      "juillet",
      "août",
      "septembre",
      "octobre",
      "novembre",
      "décembre",
      "l'été",
      "automne",
      "l'hiver",
      "printemps"
    ],
    "de": [
      "montag",
      "dienstag",
      "mittwoch",
      "donnerstag",
      "freitag",
      "samstag",
      "sonntag",
      "januar",
      "februar",
      "märz",
      "april",
      "mai",
      "juni",
      "juli",
      "august",
      "september",
      "oktober",
      "november",
      "dezember",
      "sommer",
      "herbst",
      "winter",
      "frühling"
    ],
    "it": [
      "lunedì",
      "martedì",
      "mercoledì",
      "giovedi",
      "venerdì",
      "il sabato",
      "domenica",
      "gennaio",
      "febbraio",
      "marzo",
      "aprile",
      "maggio",
      "giugno",
      "luglio",
      "agosto",
      "settembre",
      "ottobre",
      "novembre",
      "dicembre",
      "estate",
      "autunno",
      "inverno",
      "primaverile"
    ],
    "es": [
      "lunes",
      "martes",
      "miércoles",
      "jueves",
      "viernes",
      "sábado",
      "domingo",
      "enero",
      "febrero",
      "marcha",
      "abril",
      "mayo",
      "junio",
      "julio",
      "agosto",
      "septiembre",
      "octubre",
      "noviembre",
      "diciembre",
      "verano",
      "otoño",
      "invierno",
      "primavera"
    ]
  }
}
